automata/__init__.py
automata/_version.py
test_automata-2022.1.13.post1.dist-info/LICENSE.md
test_automata-2022.1.13.post1.dist-info/METADATA
test_automata-2022.1.13.post1.dist-info/WHEEL
test_automata-2022.1.13.post1.dist-info/top_level.txt
test_automata-2022.1.13.post1.dist-info/RECORD
