Metadata-Version: 2.1
Name: test-automata
Version: 2022.1.13.post1
Summary: Exabyte Automated Publishing Sandbox
Home-page: https://github.com/Exabyte-io/automata
Author: Exabyte Inc.
Author-email: info@exabyte.io
License: UNKNOWN
Platform: UNKNOWN
Classifier: Programming Language :: Python :: 3
Classifier: License :: OSI Approved :: Apache Software License
Classifier: Operating System :: OS Independent
Requires-Python: >=3.6
License-File: LICENSE.md
